my_rsa/__init__.py
my_rsa/cli.py
my_rsa/rsa.py
myrsa_encrypt-0.2.1.dist-info/LICENSE
myrsa_encrypt-0.2.1.dist-info/METADATA
myrsa_encrypt-0.2.1.dist-info/WHEEL
myrsa_encrypt-0.2.1.dist-info/top_level.txt
myrsa_encrypt-0.2.1.dist-info/RECORD
